setup.py
src/jsrn/__init__.py
src/jsrn/csv_parse.py
src/jsrn/datetimeutil.py
src/jsrn/doc_gen.py
src/jsrn/encoding.py
src/jsrn/exceptions.py
src/jsrn/registration.py
src/jsrn/resources.py
src/jsrn/utils.py
src/jsrn/validators.py
src/jsrn.egg-info/PKG-INFO
src/jsrn.egg-info/SOURCES.txt
src/jsrn.egg-info/dependency_links.txt
src/jsrn.egg-info/requires.txt
src/jsrn.egg-info/top_level.txt
src/jsrn/fields/__init__.py
src/jsrn/fields/composite.py