Metadata-Version: 1.1
Name: jsrn
Version: 0.3.2
Summary: JavaScript Resource Notation for Python
Home-page: https://github.com/timsavage/jsrn
Author: Tim Savage
Author-email: tim.savage@poweredbypenguins.org
License: LICENSE
Platform: UNKNOWN
Classifier: Intended Audience :: Developers
Classifier: Natural Language :: English
Classifier: Programming Language :: Python
Classifier: Programming Language :: Python :: 2.7
Classifier: Programming Language :: Python :: 3.3
